setup.py
custom_train_duy/__init__.py
custom_train_duy/process_data.py
custom_train_duy/train.py
custom_train_duy/train_model.py
custom_train_duy/train_model_argparam.py
custom_train_duy/utils.py
custom_train_duy.egg-info/PKG-INFO
custom_train_duy.egg-info/SOURCES.txt
custom_train_duy.egg-info/dependency_links.txt
custom_train_duy.egg-info/top_level.txt